{
    "name": "NBA",
    "children": [{
            "name": "ATL",
            "children": [{
                    "Tm": "ATL",
                    "name": "Abezy",
                    "img": "<img id='cover-img' src='data/cardSource/ATL/abezy.jpeg' />"
                },
                {
                    "Tm": "ATL",
                    "name": "Cellium",
                    "img": "<img id='cover-img' src='data/cardSource/ATL/cell.jpeg' />"
                },
                {
                    "Tm": "ATL",
                    "name": "Simp",
                    "img": "<img id='cover-img' src='data/cardSource/ATL/simp.jpeg' />"
                },
                {
                    "Tm": "ATL",
                    "name": "Slasher",
                    "img": "<img id='cover-img' src='data/cardSource/ATL/slasher.jpeg' />"
                }
            ]
        },
        {
            "name": "BOS",
            "children": [{
                    "Tm": "BOS",
                    "name": "Beans",
                    "img": "<img id='cover-img' src='data/cardSource/BOS/beans.jpeg' />"
                },
                {
                    "Tm": "BOS",
                    "name": "Kremp",
                    "img": "<img id='cover-img' src='data/cardSource/BOS/kremp.jpeg' />"
                },
                {
                    "Tm": "BOS",
                    "name": "Methodz",
                    "img": "<img id='cover-img' src='data/cardSource/BOS/meth.jpeg' />"
                },
                {
                    "Tm": "BOS",
                    "name": "Nero",
                    "img": "<img id='cover-img' src='data/cardSource/BOS/nero.jpeg' />"
                },
                {
                    "Tm": "BOS",
                    "name": "Owakening",
                    "img": "<img id='cover-img' src='data/cardSource/BOS/wake.jpeg' />"
                }
            ]
        },
        {
            "name": "FLA",
            "children": [{
                    "Tm": "FLA",
                    "name": "Brack",
                    "img": "<img id='cover-img' src='data/cardSource/FLA/brack.jpeg' />"
                },
                {
                    "Tm": "FLA",
                    "name": "Capsidal",
                    "img": "<img id='cover-img' src='data/cardSource/FLA/cap.jpeg' />"
                },
                {
                    "Tm": "FLA",
                    "name": "Felo",
                    "img": "<img id='cover-img' src='data/cardSource/FLA/felo.jpeg' />"
                },
                {
                    "Tm": "FLA",
                    "name": "Havok",
                    "img": "<img id='cover-img' src='data/cardSource/FLA/havok.jpeg' />"
                },
                {
                    "Tm": "FLA",
                    "name": "MajorManiak",
                    "img": "<img id='cover-img' src='data/cardSource/FLA/major.jpeg' />"
                }
            ]
        },
        {
            "name": "LON",
            "children": [{
                    "Tm": "LON",
                    "name": "Asim",
                    "img": "<img id='cover-img' src='data/cardSource/LON/asim.jpeg' />"
                },
                {
                    "Tm": "LON",
                    "name": "Nastie",
                    "img": "<img id='cover-img' src='data/cardSource/LON/nastie.jpeg' />"
                },
                {
                    "Tm": "LON",
                    "name": "PaulEhx",
                    "img": "<img id='cover-img' src='data/cardSource/LON/paulx.jpeg' />"
                },
                {
                    "Tm": "LON",
                    "name": "Skrapz",
                    "img": "<img id='cover-img' src='data/cardSource/LON/Skrapz.jpeg' />"
                }
            ]
        },
        {
            "name": "LAG",
            "children": [{
                    "Tm": "LAG",
                    "name": "Arcitys",
                    "img": "<img id='cover-img' src='data/cardSource/LAG/arcitys.jpeg' />"
                },
                {
                    "Tm": "LAG",
                    "name": "Assault",
                    "img": "<img id='cover-img' src='data/cardSource/LAG/assault.jpeg' />"
                },
                {
                    "Tm": "LAG",
                    "name": "Exceed",
                    "img": "<img id='cover-img' src='data/cardSource/LAG/exceed.jpeg' />"
                },
                {
                    "Tm": "LAG",
                    "name": "JoeDeceives",
                    "img": "<img id='cover-img' src='data/cardSource/LAG/joe.jpeg' />"
                }
            ]
        },
        {
            "name": "LAT",
            "children": [{
                    "Tm": "LAT",
                    "name": "Drazah",
                    "img": "<img id='cover-img' src='data/cardSource/LAT/drazah.jpeg' />"
                },
                {
                    "Tm": "LAT",
                    "name": "Envoy",
                    "img": "<img id='cover-img' src='data/cardSource/LAT/envoy.jpeg' />"
                },
                {
                    "Tm": "LAT",
                    "name": "Kenny",
                    "img": "<img id='cover-img' src='data/cardSource/LAT/ken.jpeg' />"
                },
                {
                    "Tm": "LAT",
                    "name": "Octane",
                    "img": "<img id='cover-img' src='data/cardSource/LAT/octane.jpeg' />"
                }
            ]
        }, {
            "name": "MIN",
            "children": [{
                    "Tm": "MIN",
                    "name": "Afro",
                    "img": "<img id='cover-img' src='data/cardSource/MIN/afro.jpeg' />"
                },
                {
                    "Tm": "MIN",
                    "name": "Attach",
                    "img": "<img id='cover-img' src='data/cardSource/MIN/attach.jpeg' />"
                },
                {
                    "Tm": "MIN",
                    "name": "Bance",
                    "img": "<img id='cover-img' src='data/cardSource/MIN/bance.jpeg' />"
                },
                {
                    "Tm": "MIN",
                    "name": "Cammy",
                    "img": "<img id='cover-img' src='data/cardSource/MIN/cammy.jpeg' />"
                },
                {
                    "Tm": "MIN",
                    "name": "Fame",
                    "img": "<img id='cover-img' src='data/cardSource/MIN/fame.jpeg' />"
                }
            ]
        }, {
            "name": "NYS",
            "children": [{
                    "Tm": "NYS",
                    "name": "Hydra",
                    "img": "<img id='cover-img' src='data/cardSource/NYS/hydra.jpeg' />"
                },
                {
                    "Tm": "NYS",
                    "name": "Kismet",
                    "img": "<img id='cover-img' src='data/cardSource/NYS/kis.jpeg' />"
                },
                {
                    "Tm": "NYS",
                    "name": "Priestahh",
                    "img": "<img id='cover-img' src='data/cardSource/NYS/preston.jpeg' />"
                },
                {
                    "Tm": "NYS",
                    "name": "Skyz",
                    "img": "<img id='cover-img' src='data/cardSource/NYS/Skyz.jpeg' />"
                }
            ]
        },
        {
            "name": "OPT",
            "children": [{
                    "Tm": "OPT",
                    "name": "Dashy",
                    "img": "<img id='cover-img' src='data/cardSource/OPT/dashy.jpeg' />"
                },
                {
                    "Tm": "OPT",
                    "name": "Ghosty",
                    "img": "<img id='cover-img' src='data/cardSource/OPT/ghosty.jpeg' />"
                },
                {
                    "Tm": "OPT",
                    "name": "Huke",
                    "img": "<img id='cover-img' src='data/cardSource/OPT/huke.jpeg' />"
                },
                {
                    "Tm": "OPT",
                    "name": "Illey",
                    "img": "<img id='cover-img' src='data/cardSource/OPT/illey.jpeg' />"
                },
                {
                    "Tm": "OPT",
                    "name": "Scump",
                    "img": "<img id='cover-img' src='data/cardSource/OPT/scump.jpeg' />"
                },
                {
                    "Tm": "OPT",
                    "name": "Shotzzy",
                    "img": "<img id='cover-img' src='data/cardSource/OPT/shotzy.jpeg' />"
                }
            ]
        },
        {
            "name": "SEA",
            "children": [{
                    "Tm": "SEA",
                    "name": "Accuracy",
                    "img": "<img id='cover-img' src='data/cardSource/SEA/accuracy.jpeg' />"
                },
                {
                    "Tm": "SEA",
                    "name": "Mack",
                    "img": "<img id='cover-img' src='data/cardSource/SEA/mack.jpeg' />"
                },
                {
                    "Tm": "SEA",
                    "name": "Pred",
                    "img": "<img id='cover-img' src='data/cardSource/SEA/pred.jpeg' />"
                },
                {
                    "Tm": "SEA",
                    "name": "Sib ",
                    "img": "<img id='cover-img' src='data/cardSource/SEA/sibsib.jpeg' />"
                }
            ]
        },
        {
            "name": "TOR",
            "children": [{
                    "Tm": "TOR",
                    "name": "CleanX",
                    "img": "<img id='cover-img' src='data/cardSource/TOR/cleanx.jpeg' />"
                },
                {
                    "Tm": "TOR",
                    "name": "Insight",
                    "img": "<img id='cover-img' src='data/cardSource/TOR/insight.jpeg' />"
                },
                {
                    "Tm": "TOR",
                    "name": "Hicksy",
                    "img": "<img id='cover-img' src='data/cardSource/TOR/hicksy.jpeg' />"
                },
                {
                    "Tm": "TOR",
                    "name": "Scrappy",
                    "img": "<img id='cover-img' src='data/cardSource/TOR/scrap.jpeg' />"
                }
            ]
        },
        {
            "name": "VEG",
            "children": [{
                    "Tm": "VEG",
                    "name": "2Real",
                    "img": "<img id='cover-img' src='data/cardSource/VEG/2real.jpeg' />"
                },
                {
                    "Tm": "VEG",
                    "name": "Clayster",
                    "img": "<img id='cover-img' src='data/cardSource/VEG/clay.jpeg' />"
                },
                {
                    "Tm": "VEG",
                    "name": "Prolute",
                    "img": "<img id='cover-img' src='data/cardSource/VEG/prolute.jpeg' />"
                },
                {
                    "Tm": "VEG",
                    "name": "Standy",
                    "img": "<img id='cover-img' src='data/cardSource/VEG/standy.jpeg' />"
                },
                {
                    "Tm": "VEG",
                    "name": "Temp",
                    "img": "<img id='cover-img' src='data/cardSource/VEG/temp.jpeg' />"
                },
                {
                    "Tm": "VEG",
                    "name": "TJHaly",
                    "img": "<img id='cover-img' src='data/cardSource/VEG/tjhaly.jpeg' />"
                }
            ]
        }
    ]
}